Workbook

Sheet Liquidacion IVA
A2: PERIODO | B2: CREDITO | D2: PLANILLA | F2: DIFERENCIA
A3: 2023/04 | B3: 28581391 | D3: =+Facturas!F21 -> 28581387 | F3: =+B3-D3 -> 4.12
A4: 2023/05 | B4: 371481 | D4: =+Facturas!F40 -> 371480.97 | F4: =+B4-D4 -> 0.03
A5: 2023/06 | B5: =804156-15609+30671852 -> 31460399 | D5: =+Facturas!F85 -> 37701349 | F5: =+B5-D5 -> -6240950.4
A6: 2023/07 | B6: =2690212-65454+14067870 -> 16692628 | D6: =+Facturas!F129 -> 10451679 | F6: =+B6-D6 -> 6240949.3
A7: 2023/08 | B7: =635057+21085798 -> 21720855 | D7: =+Facturas!F160 -> 21720853 | F7: =+B7-D7 -> 1.9971
A8: 2023/09 | B8: =1549483-8112+2286704 -> 3828075 | D8: =+Facturas!F183 -> 3828072.8 | F8: =+B8-D8 -> 2.1863
A9: 2023/10 | B9: =12095793+2048376 -> 14144169 | D9: =+Facturas!F224 -> 14144168 | F9: =+B9-D9 -> 0.54300001
A10: 2023/11 | B10: 1176728 | D10: =+Facturas!F267 -> 4064811.9 | F10: =+B10-D10 -> -2888083.9
A11: 2023/12
A14: PERIODO | B14: DEBITOS | C14: CRÉDITOS | L14: CRED ANT
B15: 563 | C15: 562 | D15: 520 | E15: 528 | F15: 535 | G15: 544 | H15: 779 | I15: TOTAL | L15: 504
A16: 2023/04 | B16: 0 | C16: 2529312 | D16: 28581391 | E16: 0 | F16: 0 | G16: 0 | H16: 0 | I16: =SUM(D16:H16) -> 28581391 | J16: =+B3-I16 -> 0 | L16: 0
A17: 2023/05 | B17: 0 | C17: 722970 | D17: 371481 | E17: 0 | F17: 0 | G17: 0 | H17: 0 | I17: =SUM(D17:H17) -> 371481 | J17: =+B4-I17 -> 0 | L17: 0
A18: 2023/06 | B18: 0 | C18: 3679423 | D18: 804156 | E18: -15609 | F18: 30671852 | G18: 0 | H18: 0 | I18: =SUM(D18:H18) -> 31460399 | J18: =+B5-I18 -> 0 | L18: 35314377 | M18: =+D3+D4-L18 -> -6361509.2
A19: 2023/07 | I19: =SUM(D19:H19) -> 0 | J19: =+B6-I19 -> 16692628
A20: 2023/08 | I20: =SUM(D20:H20) -> 0 | J20: =+B7-I20 -> 21720855
A21: 2023/09 | I21: =SUM(D21:H21) -> 0 | J21: =+B8-I21 -> 3828075
A22: 2023/10 | I22: =SUM(D22:H22) -> 0 | J22: =+B9-I22 -> 14144169
A23: 2023/11 | I23: =SUM(D23:H23) -> 0 | J23: =+B10-I23 -> 1176728
A24: 2023/12 | I24: =SUM(D24:H24) -> 0 | J24: =+B11-I24 -> 0
A28: 562 - MONTO SIN DERECHO A CRÉDITO FISCAL
A29: 520 - CREDITOS RECIBIDOS Y REINTEGRADOS
A30: 528 - NOTAS DE CRÉDITO
A31: 535 - CREDITOS, RECUPEROS Y REINTEGROS
A32: 544 - RECUPERO IMPUESTO AL DIESEL
A33: 779 - MONTO DE IVA POSTERGADO

Sheet Facturas
A1: FECHA | B1: FACTURA | C1: PROVEEDOR | D1: NETO | E1: EXENTO | F1: IVA | G1: BRUTO | H1: DETALLE GTO | I1: PAGO | J1: MEDIO | L1: COMP
A3: 44994 | B3: 000000041 | C3: RSM CHILE LTDA | D3: 0 | E3: 321152 | F3: =+D3*0.19 -> 0 | G3: =SUM(D3:F3) -> 321152 | H3: ESTUDIO CONTABLE | I3: 45007 | J3: TRANSFERENCIA | L3: 2023/03
A4: 44994 | B4: 000000110 | C4: RSM CHILE LTDA | D4: 0 | E4: 722592 | F4: =+D4*0.19 -> 0 | G4: =SUM(D4:F4) -> 722592 | H4: ESTUDIO CONTABLE | I4: 45007 | J4: TRANSFERENCIA | L4: 2023/03
A5: 44994 | B5: 000000193 | C5: RSM CHILE LTDA | D5: 0 | E5: 722592 | F5: =+D5*0.19 -> 0 | G5: =SUM(D5:F5) -> 722592 | H5: ESTUDIO CONTABLE | I5: 45007 | J5: TRANSFERENCIA | L5: 2023/03
A6: 44999 | B6: 000000234 | C6: RSM CHILE LTDA | D6: 0 | E6: 722826 | F6: =+D6*0.19 -> 0 | G6: =SUM(D6:F6) -> 722826 | H6: ESTUDIO CONTABLE | I6: 45007 | J6: TRANSFERENCIA | L6: 2023/03
A7: 44999 | B7: 000000235 | C7: RSM CHILE LTDA | D7: 0 | E7: 722826 | F7: =+D7*0.19 -> 0 | G7: =SUM(D7:F7) -> 722826 | H7: ESTUDIO CONTABLE | I7: 45007 | J7: TRANSFERENCIA | L7: 2023/03
A8: 44999 | B8: 000000236 | C8: RSM CHILE LTDA | D8: 0 | E8: 963768 | F8: =+D8*0.19 -> 0 | G8: =SUM(D8:F8) -> 963768 | H8: ESTUDIO CONTABLE | I8: 45007 | J8: TRANSFERENCIA | L8: 2023/03
A9: 45006 | B9: 000000269 | C9: RSM CHILE LTDA | D9: 0 | E9: 413175 | F9: =+D9*0.19 -> 0 | G9: =SUM(D9:F9) -> 413175 | H9: ESTUDIO CONTABLE | I9: 45007 | J9: TRANSFERENCIA | L9: 2023/03
D10: =SUM(D3:D9) -> 0 | E10: =SUM(E3:E9) -> 4588931 | F10: =SUM(F3:F9) -> 0 | G10: =SUM(G3:G9) -> 4588931
A12: 45009 | B12: 000085424 | C12: PLAZA EL BOSQUE NUEVA LAS CONDES | D12: 280986 | E12: 0 | F12: =+D12*0.19 -> 53387.34 | G12: =SUM(D12:F12) -> 334373.34 | H12: HOTEL FERNANDO | L12: 2023/04
A13: 45010 | B13: 000036018 | C13: HOTELES DIRECTOR LTDA | D13: 2002000 | E13: 0 | F13: =+D13*0.19 -> 380380 | G13: =SUM(D13:F13) -> 2382380 | H13: HOTEL CURSO BELDEN | I13: 44995 | J13: TRANSFERENCIA | L13: 2023/04
A14: 45019 | B14: 000000350 | C14: RSM CHILE LTDA | D14: 0 | E14: 948492 | F14: =+D14*0.19 -> 0 | G14: =SUM(D14:F14) -> 948492 | H14: ESTUDIO CONTABLE | I14: 45033 | J14: TRANSFERENCIA | L14: 2023/04
A15: 45019 | B15: 000002098 | C15: RSM CHILE LTDA | D15: 0 | E15: 1580820 | F15: =+D15*0.19 -> 0 | G15: =SUM(D15:F15) -> 1580820 | H15: ESTUDIO CONTABLE | I15: 45062 | J15: TRANSFERENCIA | L15: 2023/04
A16: 45020 | B16: 000326069 | C16: SONDA SA | D16: 124665425 | E16: 0 | F16: =+D16*0.19 -> 23686431 | G16: =SUM(D16:F16) -> 1.4835186e+08 | H16: EQUIPOS CISCO | I16: 45028 | J16: TRANSFERENCIA | L16: 2023/04
A17: 45028 | B17: 000126973 | C17: KOLFF SPA | D17: 6244605 | E17: 0 | F17: =+D17*0.19 -> 1186474.9 | G17: =SUM(D17:F17) -> 7431080 | H17: EQUIPOS RITTAL | I17: 45030 | J17: TRANSFERENCIA | L17: 2023/04
A18: 45028 | B18: 000126975 | C18: KOLFF SPA | D18: 16999750 | E18: 0 | F18: =+D18*0.19 -> 3229952.5 | G18: =SUM(D18:F18) -> 20229702 | H18: SERVICIOS | I18: 45030 | J18: TRANSFERENCIA | L18: 2023/04
A19: 45034 | B19: 006055073 | C19: BANCO ITAU CORPBANCA | D19: 88930 | E19: 0 | F19: =+D19*0.19 -> 16896.7 | G19: =SUM(D19:F19) -> 105826.7 | H19: GASTOS BANCARIOS | I19: 45034 | J19: DEBITO BANCO | L19: 2023/04
A20: 45041 | B20: 006063030 | C20: BANCO ITAU CORPBANCA | D20: 146656 | E20: 0 | F20: =+D20*0.19 -> 27864.64 | G20: =SUM(D20:F20) -> 174520.64 | H20: GASTOS BANCARIOS | I20: 45041 | J20: DEBITO BANCO | L20: 2023/04
D21: =SUM(D12:D20) -> 150428352 | E21: =SUM(E12:E20) -> 2529312 | F21: =SUM(F12:F20) -> 28581387 | G21: =SUM(G12:G20) -> 1.8153905e+08
A23: 45048 | B23: 000000468 | C23: RSM CHILE LTDA | D23: 0 | E23: 722970 | F23: =+D23*0.19 -> 0 | G23: =SUM(D23:F23) -> 722970 | H23: ESTUDIO CONTABLE | I23: 45062 | J23: TRANSFERENCIA | L23: 2023/05
A24: 45050 | B24: 000000503 | C24: EASY POINT LOGISTICS SPA | D24: 215345 | E24: 0 | F24: =+D24*0.19 -> 40915.55 | G24: =SUM(D24:F24) -> 256260.55 | H24: SHIP 0004 | I24: 45050 | J24: EASY POINT | L24: 2023/05
A25: 45051 | B25: 000696508 | C25: FEDEX EXPRESS CHILE SPA | D25: 176502 | E25: 0 | F25: =+D25*0.19 -> 33535.38 | G25: =SUM(D25:F25) -> 210037.38 | H25: SHIP 0004 | I25: 45050 | J25: EASY POINT | L25: 2023/05
A26: 45055 | B26: 006085902 | C26: BANCO ITAU CORPBANCA | D26: 1432 | E26: 0 | F26: =+D26*0.19 -> 272.08 | G26: =SUM(D26:F26) -> 1704.08 | H26: GASTOS BANCARIOS | I26: 45055 | J26: DEBITO BANCO | L26: 2023/05
A27: 45055 | B27: 006097076 | C27: BANCO ITAU CORPBANCA | D27: 89662 | E27: 0 | F27: =+D27*0.19 -> 17035.78 | G27: =SUM(D27:F27) -> 106697.78 | H27: GASTOS BANCARIOS | I27: 45055 | J27: DEBITO BANCO | L27: 2023/05
A28: 45063 | B28: 003519638 | C28: DHL EXPRESS (CHILE) LTDA | D28: 263907 | E28: 0 | F28: =+D28*0.19 -> 50142.33 | G28: =SUM(D28:F28) -> 314049.33 | H28: SHIP 0005 | I28: 45062 | J28: EASY POINT | L28: 2023/05
A29: 45064 | B29: 000062043 | C29: ARANEDA MEZA, MARIO | D29: 128425 | E29: 0 | F29: =+D29*0.19 -> 24400.75 | G29: =SUM(D29:F29) -> 152825.75 | H29: SHIP 0004 | I29: 45050 | J29: EASY POINT | L29: 2023/05
A30: 45064 | B30: 000062044 | C30: ARANEDA MEZA, MARIO | D30: 128425 | E30: 0 | F30: =+D30*0.19 -> 24400.75 | G30: =SUM(D30:F30) -> 152825.75 | H30: SHIP 0005 | I30: 45062 | J30: EASY POINT | L30: 2023/05
A31: 45065 | B31: 000957357 | C31: UPS DE CHILE LTDA | D31: 116071 | E31: 0 | F31: =+D31*0.19 -> 22053.49 | G31: =SUM(D31:F31) -> 138124.49 | H31: SHIP 0008 | I31: 45064 | J31: TRANSFERENCIA | L31: 2023/05
A32: 45065 | B32: 000957358 | C32: UPS DE CHILE LTDA | D32: 116071 | E32: 0 | F32: =+D32*0.19 -> 22053.49 | G32: =SUM(D32:F32) -> 138124.49 | H32: SHIP 0009 | I32: 45064 | J32: TRANSFERENCIA | L32: 2023/05
A33: 45062 | B33: 000000533 | C33: EASY POINT LOGISTICS SPA | D33: 215884 | E33: 0 | F33: =+D33*0.19 -> 41017.96 | G33: =SUM(D33:F33) -> 256901.96 | H33: SHIP 0005 | I33: 45062 | J33: EASY POINT | L33: 2023/05
A34: 45071 | B34: 002883004 | C34: SERV AEROPORTUARIOS AEROSAN SA | D34: 100933 | E34: 0 | F34: =+D34*0.19 -> 19177.27 | G34: =SUM(D34:F34) -> 120110.27 | H34: SHIP 0006 | I34: 45069 | J34: EASY POINT | L34: 2023/05
... A39: 45076 | B39: 000062154 | C39: ARANEDA MEZA, MARIO | D39: 83217 | E39: 0 | F39: =+D39*0.19 -> 15811.23 | G39: =SUM(D39:F39) -> 99028.23 | H39: SHIP 0006 | I39: 45069 | J39: EASY POINT | L39: 2023/05
D40: =SUM(D23:D39) -> 1955163 | E40: =SUM(E23:E39) -> 722970 | F40: =SUM(F23:F39) -> 371480.97 | G40: =SUM(G23:G39) -> 3049614
A42: 45050 | B42: 3670087762-5 | C42: TESORERIA GENERAL DE LA REPUBLICA | D42: 0 | E42: =379.94*805.21 -> 305931.49 | F42: =1275.32*805.21 -> 1026900.4 | G42: =SUM(D42:F42) -> 1332831.9 | H42: SHIP 0004 | I42: 45050 | J42: EASY POINT | L42: 2023/06
A43: 45062 | B43: 3670088084-7 | C43: TESORERIA GENERAL DE LA REPUBLICA | D43: 0 | E43: =466.77*805.21 -> 375847.87 | F43: =1566.78*805.21 -> 1261586.9 | G43: =SUM(D43:F43) -> 1637434.8 | H43: SHIP 0005 | I43: 45062 | J43: EASY POINT | L43: 2023/06
A44: 45064 | B44: 401959436-5 | C44: TESORERIA GENERAL DE LA REPUBLICA | D44: 0 | E44: =107.5*805.21 -> 86560.075 | F44: =360.85*805.21 -> 290560.03 | G44: =SUM(D44:F44) -> 377120.1 | H44: SHIP 0009 | I44: 45064 | J44: UPS | L44: 2023/06
A45: 45064 | B45: 401959437-3 | C45: TESORERIA GENERAL DE LA REPUBLICA | D45: 0 | E45: =162.21*805.21 -> 130613.11 | F45: =544.47*805.21 -> 438412.69 | G45: =SUM(D45:F45) -> 569025.8 | H45: SHIP 0008 | I45: 45064 | J45: UPS | L45: 2023/06
A46: 45069 | B46: 000229152 | C46: MSL CHILE SA | D46: 40012 | E46: 0 | F46: =+D46*0.19 -> 7602.28 | G46: =SUM(D46:F46) -> 47614.28 | H46: SHIP 0006 | I46: 45069 | J46: EASY POINT | L46: 2023/06
A47: 45069 | B47: 000052012 | C47: MSL CHILE SA | D47: 0 | E47: 1000956 | F47: =+D47*0.19 -> 0 | G47: =SUM(D47:F47) -> 1000956 | H47: SHIP 0006 | I47: 45069 | J47: EASY POINT | L47: 2023/06
A48: 45069 | B48: 000000551 | C48: EASY POINT LOGISTICS SPA | D48: 216030 | E48: 0 | F48: =+D48*0.19 -> 41045.7 | G48: =SUM(D48:F48) -> 257075.7 | H48: SHIP 0006 | I48: 45069 | J48: EASY POINT | L48: 2023/06
A49: 45070 | B49: 3670088216-5 | C49: TESORERIA GENERAL DE LA REPUBLICA | D49: 0 | E49: 0 | F49: =1096.19*805.21 -> 882663.15 | G49: =SUM(D49:F49) -> 882663.15 | H49: SHIP 0006 | I49: 45069 | J49: EASY POINT | L49: 2023/06
A50: 45070 | B50: 3670088217-3 | C50: TESORERIA GENERAL DE LA REPUBLICA | D50: 0 | E50: =645.57*805.21 -> 519819.42 | F50: =2166.98*805.21 -> 1744874 | G50: =SUM(D50:F50) -> 2264693.4 | H50: SHIP 0006 | I50: 45069 | J50: EASY POINT | L50: 2023/06
A51: 45070 | B51: 000000541 | C51: EASY POINT LOGISTICS SPA | D51: 43581 | E51: 0 | F51: =+D51*0.19 -> 8280.39 | G51: =SUM(D51:F51) -> 51861.39 | H51: SHIP 0006 | I51: 45069 | J51: EASY POINT | L51: 2023/06
A52: 45071 | B52: 0236665984 | C52: TESORERIA GENERAL DE LA REPUBLICA | D52: 0 | E52: 0 | F52: =216.88*805.21 -> 174633.94 | G52: =SUM(D52:F52) -> 174633.94 | H52: SHIP 0011 | I52: 45075 | J52: DHL | L52: 2023/06
A53: 45075 | B53: 401963068-K | C53: TESORERIA GENERAL DE LA REPUBLICA | D53: 0 | E53: =155.88*805.21 -> 125516.13 | F53: =523.24*805.21 -> 421318.08 | G53: =SUM(D53:F53) -> 546834.22 | H53: SHIP 0012 | I53: 45075 | J53: UPS | L53: 2023/06
A54: 45077 | B54: 000000564 | C54: EASY POINT LOGISTICS SPA | D54: 108099 | E54: 0 | F54: =+D54*0.19 -> 20538.81 | G54: =SUM(D54:F54) -> 128637.81 | H54: SHIP 0008 | I54: 45092 | J54: TRANSFERENCIA | L54: 2023/06
A55: 45077 | B55: 000000565 | C55: EASY POINT LOGISTICS SPA | D55: 108099 | E55: 0 | F55: =+D55*0.19 -> 20538.81 | G55: =SUM(D55:F55) -> 128637.81 | H55: SHIP 0009 | I55: 45092 | J55: TRANSFERENCIA | L55: 2023/06
A56: 45077 | B56: 000000566 | C56: EASY POINT LOGISTICS SPA | D56: 108099 | E56: 0 | F56: =+D56*0.19 -> 20538.81 | G56: =SUM(D56:F56) -> 128637.81 | H56: SHIP 0011 | I56: 45092 | J56: TRANSFERENCIA | L56: 2023/06
A57: 45077 | B57: 000000567 | C57: EASY POINT LOGISTICS SPA | D57: 108099 | E57: 0 | F57: =+D57*0.19 -> 20538.81 | G57: =SUM(D57:F57) -> 128637.81 | H57: SHIP 0012 | I57: 45092 | J57: TRANSFERENCIA | L57: 2023/06
A58: 45078 | B58: 000000599 | C58: RSM CHILE LTDA | D58: 0 | E58: 730449 | F58: =+D58*0.19 -> 0 | G58: =SUM(D58:F58) -> 730449 | H58: ESTUDIO CONTABLE | I58: 45092 | J58: TRANSFERENCIA | L58: 2023/06
A59: 45082 | B59: 001280624 | C59: MAERSK LOGISTICS SPA | D59: 119696 | E59: 0 | F59: =+D59*0.19 -> 22742.24 | G59: =SUM(D59:F59) -> 142438.24 | H59: SHIP 0010 | I59: 45084 | J59: EASY POINT | L59: 2023/06
A60: 45082 | B60: 000170809 | C60: MAERSK LOGISTICS SPA | D60: 0 | E60: 928925 | F60: =+D60*0.19 -> 0 | G60: =SUM(D60:F60) -> 928925 | H60: SHIP 0010 | I60: 45084 | J60: EASY POINT | L60: 2023/06
A61: 45084 | B61: 3670088467-2 | C61: TESORERIA GENERAL DE LA REPUBLICA | D61: 0 | E61: =464.96*802.14 -> 372963.01 | F61: =1560.71*802.14 -> 1251907.9 | G61: =SUM(D61:F61) -> 1624870.9 | H61: SHIP 0010 | I61: 45086 | J61: EASY POINT | L61: 2023/06
A62: 45084 | B62: 3670088462-1 | C62: TESORERIA GENERAL DE LA REPUBLICA | D62: 0 | E62: 0 | F62: =14529.2*802.14 -> 11654452 | G62: =SUM(D62:F62) -> 11654452 | H62: SHIP 0010 | I62: 45086 | J62: EASY POINT | L62: 2023/06
A63: 45085 | B63: 000000572 | C63: EASY POINT LOGISTICS SPA | D63: 219799 | E63: 0 | F63: =+D63*0.19 -> 41761.81 | G63: =SUM(D63:F63) -> 261560.81 | H63: SHIP 0010 | I63: 45086 | J63: EASY POINT | L63: 2023/06
A64: 45085 | B64: 000000579 | C64: EASY POINT LOGISTICS SPA | D64: 216365 | E64: 0 | F64: =+D64*0.19 -> 41109.35 | G64: =SUM(D64:F64) -> 257474.35 | H64: SHIP 0010 | I64: 45086 | J64: EASY POINT | L64: 2023/06
A65: 45086 | B65: 002885884 | C65: SERV AEROPORTUARIOS AEROSAN SA | D65: 290592 | E65: 0 | F65: =+D65*0.19 -> 55212.48 | G65: =SUM(D65:F65) -> 345804.48 | H65: SHIP 0010 | I65: 45086 | J65: EASY POINT | L65: 2023/06
A66: 45088 | B66: 000005627 | C66: MOYA VARAS, MARINA | D66: 40000 | E66: 0 | F66: =+D66*0.19 -> 7600 | G66: =SUM(D66:F66) -> 47600 | H66: SHIP 0010 | I66: 45086 | J66: EASY POINT | L66: 2023/06
A67: 45089 | B67: 001283967 | C67: MAERSK LOGISTICS SPA | D67: 118080 | E67: 0 | F67: =+D67*0.19 -> 22435.2 | G67: =SUM(D67:F67) -> 140515.2 | H67: SHIP 0013 | I67: 45092 | J67: EASY POINT | L67: 2023/06
A68: 45089 | B68: 000170849 | C68: MAERSK LOGISTICS SPA | D68: 0 | E68: 1019093 | F68: =+D68*0.19 -> 0 | G68: =SUM(D68:F68) -> 1019093 | H68: SHIP 0013 | I68: 45092 | J68: EASY POINT | L68: 2023/06
A69: 45090 | B69: 000000587 | C69: EASY POINT LOGISTICS SPA | D69: 257664 | E69: 0 | F69: =+D69*0.19 -> 48956.16 | G69: =SUM(D69:F69) -> 306620.16 | H69: SHIP 0013 | I69: 45093 | J69: EASY POINT | L69: 2023/06
A70: 45092 | B70: 000062404 | C70: ARANEDA MEZA, MARIO | D70: 246487 | E70: 0 | F70: =+D70*0.19 -> 46832.53 | G70: =SUM(D70:F70) -> 293319.53 | H70: SHIP 0010 | I70: 45086 | J70: EASY POINT | L70: 2023/06
A71: 45092 | B71: 000062405 | C71: ARANEDA MEZA, MARIO | D71: 128057 | E71: 0 | F71: =+D71*0.19 -> 24330.83 | G71: =SUM(D71:F71) -> 152387.83 | H71: SHIP 0010 | I71: 45086 | J71: EASY POINT | L71: 2023/06
A72: 45093 | B72: 3670088511-3 | C72: TESORERIA GENERAL DE LA REPUBLICA | D72: 0 | E72: 0 | F72: =16625.29*802.14 -> 13335810 | G72: =SUM(D72:F72) -> 13335810 | H72: SHIP 0013 | I72: 45093 | J72: EASY POINT | L72: 2023/06
A73: 45093 | B73: 3670088536-9 | C73: TESORERIA GENERAL DE LA REPUBLICA | D73: 0 | E73: =575.49*802.14 -> 461623.55 | F73: =1931.74*802.14 -> 1549525.9 | G73: =SUM(D73:F73) -> 2011149.5 | H73: SHIP 0013 | I73: 45093 | J73: EASY POINT | L73: 2023/06
A74: 45096 | B74: 002887605 | C74: SERV AEROPORTUARIOS AEROSAN SA | D74: 326736 | E74: 0 | F74: =+D74*0.19 -> 62079.84 | G74: =SUM(D74:F74) -> 388815.84 | H74: SHIP 0013 | I74: 45093 | J74: EASY POINT | L74: 2023/06
A75: 45096 | B75: 000000607 | C75: EASY POINT LOGISTICS SPA | D75: 39668 | E75: 0 | F75: =+D75*0.19 -> 7536.92 | G75: =SUM(D75:F75) -> 47204.92 | H75: SHIP 0010 | I75: 45086 | J75: EASY POINT | L75: 2023/06
A76: 45096 | B76: 006154470 | C76: BANCO ITAU CORPBANCA | D76: 87269 | E76: 0 | F76: =+D76*0.19 -> 16581.11 | G76: =SUM(D76:F76) -> 103850.11 | H76: GASTOS BANCARIOS | I76: 45096 | J76: DEBITO BANCARIO | L76: 2023/06
A77: 45096 | B77: 000002563 | C77: ARANEDA MEZA, MARIO | D77: -82150 | E77: 0 | F77: =+D77*0.19 -> -15608.5 | G77: =SUM(D77:F77) -> -97758.5 | H77: SHIP 0010 | I77: 45086 | J77: EASY POINT | L77: 2023/06
A78: 45097 | B78: 000005653 | C78: MOYA VARAS, MARINA | D78: 43000 | E78: 0 | F78: =+D78*0.19 -> 8170 | G78: =SUM(D78:F78) -> 51170 | H78: SHIP 0013 | I78: 45093 | J78: EASY POINT | L78: 2023/06
A79: 45099 | B79: 000000051 | C79: GRUPO MONTECARLO SPA | D79: 865546 | E79: 0 | F79: =+D79*0.19 -> 164453.74 | G79: =SUM(D79:F79) -> 1029999.7 | H79: MOVILIZACION | I79: 45093 | J79: TRANSFERENCIA | L79: 2023/06
A80: 45104 | B80: 000062535 | C80: ARANEDA MEZA, MARIO | D80: 277460 | E80: 0 | F80: =+D80*0.19 -> 52717.4 | G80: =SUM(D80:F80) -> 330177.4 | H80: SHIP 0013 | I80: 45093 | J80: EASY POINT | L80: 2023/06
A81: 45104 | B81: 000062536 | C81: ARANEDA MEZA, MARIO | D81: 45907 | E81: 0 | F81: =+D81*0.19 -> 8722.33 | G81: =SUM(D81:F81) -> 54629.33 | H81: SHIP 0013 | I81: 45093 | J81: EASY POINT | L81: 2023/06
A82: 45105 | B82: 3670088717-5 | C82: TESORERIA GENERAL DE LA REPUBLICA | D82: 0 | E82: =1069.68*802.14 -> 858033.12 | F82: =3590.59*802.14 -> 2880155.9 | G82: =SUM(D82:F82) -> 3738189 | H82: SHIP 0007 | I82: 45104 | J82: EASY POINT | L82: 2023/06
A83: 45105 | B83: 000005670 | C83: MOYA VARAS, MARINA | D83: 50000 | E83: 0 | F83: =+D83*0.19 -> 9500 | G83: =SUM(D83:F83) -> 59500 | H83: SHIP 0007 | I83: 45104 | J83: EASY POINT | L83: 2023/06
A84: 45107 | B84: 000062601 | C84: ARANEDA MEZA, MARIO | D84: 128057 | E84: 0 | F84: =+D84*0.19 -> 24330.83 | G84: =SUM(D84:F84) -> 152387.83 | H84: SHIP 0007 | I84: 45104 | J84: EASY POINT | L84: 2023/06
D85: =SUM(D42:D84) -> 4150252 | E85: =SUM(E42:E84) -> 6916330.8 | F85: =SUM(F42:F84) -> 37701349 | G85: =SUM(G42:G84) -> 48767932
A87: 45093 | B87: 000000616 | C87: EASY POINT LOGISTICS SPA | D87: 216436 | E87: 0 | F87: =+D87*0.19 -> 41122.84 | G87: =SUM(D87:F87) -> 257558.84 | H87: SHIP 0013 | I87: 45093 | J87: EASY POINT | L87: 2023/07
A88: 45099 | B88: 000000615 | C88: EASY POINT LOGISTICS SPA | D88: 40095 | E88: 0 | F88: =+D88*0.19 -> 7618.05 | G88: =SUM(D88:F88) -> 47713.05 | H88: SHIP 0013 | I88: 45093 | J88: EASY POINT | L88: 2023/07
A89: 45100 | B89: 000000635 | C89: EASY POINT LOGISTICS SPA | D89: 216486 | E89: 0 | F89: =+D89*0.19 -> 41132.34 | G89: =SUM(D89:F89) -> 257618.34 | H89: SHIP 0007 | I89: 45104 | J89: EASY POINT | L89: 2023/07
A90: 45104 | B90: 000025975 | C90: TIBA CHILE SPA | D90: 264540 | E90: 0 | F90: =+D90*0.19 -> 50262.6 | G90: =SUM(D90:F90) -> 314802.6 | H90: SHIP 0007 | I90: 45104 | J90: EASY POINT | L90: 2023/07
A91: 45104 | B91: 000038729 | C91: TIBA CHILE SPA | D91: 0 | E91: 3431304 | F91: =+D91*0.19 -> 0 | G91: =SUM(D91:F91) -> 3431304 | H91: SHIP 0007 | I91: 45104 | J91: EASY POINT | L91: 2023/07
A92: 45105 | B92: 000904648 | C92: FAST AIR ALMACENES DE CARGA SA | D92: 100789 | E92: 0 | F92: =+D92*0.19 -> 19149.91 | G92: =SUM(D92:F92) -> 119938.91 | H92: SHIP 0007 | I92: 45104 | J92: EASY POINT | L92: 2023/07
A93: 45107 | B93: 000000629 | C93: EASY POINT LOGISTICS SPA | D93: 54879 | E93: 0 | F93: =+D93*0.19 -> 10427.01 | G93: =SUM(D93:F93) -> 65306.01 | H93: SHIP 0007 | I93: 45104 | J93: EASY POINT | L93: 2023/07
A94: 45110 | B94: 000000754 | C94: RSM CHILE LTDA | D94: 0 | E94: 721494 | F94: =+D94*0.19 -> 0 | G94: =SUM(D94:F94) -> 721494 | H94: ESTUDIO CONTABLE | I94: 45124 | J94: TRANSFERENCIA | L94: 2023/07
A95: 45111 | B95: 000127306 | C95: KOLFF SPA | D95: 9123073 | E95: 0 | F95: =+D95*0.19 -> 1733383.9 | G95: =SUM(D95:F95) -> 10856457 | H95: EQUIPOS RITTAL | I95: 45152 | J95: TRANSFERENCIA | L95: 2023/07
A96: 45112 | B96: 003559618 | C96: DHL EXPRESS (CHILE) LTDA | D96: 60067 | E96: 0 | F96: =+D96*0.19 -> 11412.73 | G96: =SUM(D96:F96) -> 71479.73 | H96: SHIP 0017 | I96: 45117 | J96: TRANSFERENCIA | L96: 2023/07
A97: 45112 | B97: 0236719180 | C97: TESORERIA GENERAL DE LA REPUBLICA | D97: 0 | E97: =55.49*800.89 -> 44441.386 | F97: =186.25*800.89 -> 149165.76 | G97: =SUM(D97:F97) -> 193607.15 | H97: SHIP 0017 | I97: 45117 | J97: DHL | L97: 2023/07
A98: 45114 | B98: 000000641 | C98: EASY POINT LOGISTICS SPA | D98: 99282 | E98: 0 | F98: =+D98*0.19 -> 18863.58 | G98: =SUM(D98:F98) -> 118145.58 | H98: SHIP 0015 | I98: 45117 | J98: EASY POINT | L98: 2023/07
A99: 45114 | B99: 3670088869-4 | C99: TESORERIA GENERAL DE LA REPUBLICA | D99: 0 | E99: 0 | F99: =6113.97*800.89 -> 4896617.4 | G99: =SUM(D99:F99) -> 4896617.4 | H99: SHIP 0015 | I99: 45117 | J99: EASY POINT | L99: 2023/07
A100: 45117 | B100: 000026188 | C100: TIBA CHILE SPA | D100: 264863 | E100: 0 | F100: =+D100*0.19 -> 50323.97 | G100: =SUM(D100:F100) -> 315186.97 | H100: SHIP 0015 | I100: 45117 | J100: EASY POINT | L100: 2023/07
A101: 45117 | B101: 006186918 | C101: BANCO ITAU CORPBANCA | D101: 88494 | E101: 0 | F101: =+D101*0.19 -> 16813.86 | G101: =SUM(D101:F101) -> 105307.86 | H101: GASTOS BANCARIOS | I101: 45117 | J101: DEBITO BANCARIO | L101: 2023/07
A102: 45117 | B102: 000039026 | C102: TIBA CHILE SPA | D102: 0 | E102: 737559 | F102: =+D102*0.19 -> 0 | G102: =SUM(D102:F102) -> 737559 | H102: SHIP 0015 | I102: 45117 | J102: EASY POINT | L102: 2023/07
A103: 45120 | B103: 000000652 | C103: EASY POINT LOGISTICS SPA | D103: 108273 | E103: 0 | F103: =+D103*0.19 -> 20571.87 | G103: =SUM(D103:F103) -> 128844.87 | H103: SHIP 0017 | I103: 45124 | J103: TRANSFERENCIA | L103: 2023/07
A104: 45120 | B104: 000000653 | C104: EASY POINT LOGISTICS SPA | D104: 216546 | E104: 0 | F104: =+D104*0.19 -> 41143.74 | G104: =SUM(D104:F104) -> 257689.74 | H104: SHIP 0015 | I104: 45117 | J104: EASY POINT | L104: 2023/07
A105: 45121 | B105: 000770105 | C105: DEPOCARGO SPA | D105: 51241 | E105: 0 | F105: =+D105*0.19 -> 9735.79 | G105: =SUM(D105:F105) -> 60976.79 | H105: SHIP 0015 | I105: 45117 | J105: EASY POINT | L105: 2023/07
A106: 45123 | B106: 000005714 | C106: MOYA VARAS, MARINA PATRICIA | D106: 40000 | E106: 0 | F106: =+D106*0.19 -> 7600 | G106: =SUM(D106:F106) -> 47600 | H106: SHIP 0015 | I106: 45117 | J106: EASY POINT | L106: 2023/07
A107: 45124 | B107: 000000663 | C107: EASY POINT LOGISTICS SPA | D107: 40672 | E107: 0 | F107: =+D107*0.19 -> 7727.68 | G107: =SUM(D107:F107) -> 48399.68 | H107: SHIP 0014 | I107: 45132 | J107: EASY POINT | L107: 2023/07
A108: 45124 | B108: 000062789 | C108: ARANEDA MEZA, MARIO HUMBERTO | D108: 144426 | E108: 0 | F108: =+D108*0.19 -> 27440.94 | G108: =SUM(D108:F108) -> 171866.94 | H108: SHIP 0015 | I108: 45117 | J108: EASY POINT | L108: 2023/07
A109: 45124 | B109: 401980354-1 | C109: TESORERIA GENERAL DE LA REPUBLICA | D109: 0 | E109: =47.62*800.89 -> 38138.382 | F109: =159.85*800.89 -> 128022.27 | G109: =SUM(D109:F109) -> 166160.65 | H109: SHIP 0018 | I109: 45124 | J109: UPS | L109: 2023/07
...

Sheet Easy Point
A1: FECHA | B1: NUMERO | C1: TITULAR | D1: MONTO | E1: SHIP
A2: 45050 | B2: 000000503 | C2: EASY POINT LOGISTICS SPA | D2: 256260.55 | E2: SHIP 0004 | G2: PAGOS MULTIPLES
A3: 45051 | B3: 000696508 | C3: FEDEX EXPRESS CHILE SPA | D3: 210037.38 | E3: SHIP 0004
A4: 45051 | B4: 3670087762-5 | C4: TESORERIA GENERAL DE LA REPUBLICA | D4: 1332831.9 | E4: SHIP 0004 | G4: 45069 | H4: SHIP 0004 | I4: 42587 | J4: SALDO
A5: 45064 | B5: 000062043 | C5: ARANEDA MEZA, MARIO | D5: 152825.75 | E5: SHIP 0004 | G5: 45069 | H5: SHIP 0005 | I5: 146606 | J5: SALDO
C6: MENSAJERIA | D6: 17000 | G6: 45069 | H6: SHIP 0006 | I6: 4904470 | J6: IMPO
D7: =SUM(D2:D6) -> 1968955.6 | I7: =SUM(I4:I6) -> 5093663
A8: 45051 | B8: SHIP 0004 | C8: TRANSFERENCIA BANCARIA | D8: -1926369
A9: 45069 | B9: VS SHIPS | C9: TRANSFERENCIA BANCARIA | D9: =-I4 -> -42587 | G9: 45112 | H9: SHIP 0010 | I9: 170853 | J9: SALDO
D10: =SUM(D7:D9) -> -0.4154 | G10: 45112 | H10: SHIP 0013 | I10: 195857 | J10: SALDO
G11: 45112 | H11: SHIP 0007 | I11: -184373 | J11: SALDO
A12: 45062 | B12: 3670088084-7 | C12: TESORERIA GENERAL DE LA REPUBLICA | D12: 1637434.8 | E12: SHIP 0005 | I12: =SUM(I9:I11) -> 182337
A13: 45063 | B13: 003519638 | C13: DHL EXPRESS (CHILE) LTDA | D13: 314049.33 | E13: SHIP 0005
A14: 45064 | B14: 000062044 | C14: ARANEDA MEZA, MARIO | D14: 152825.75 | E14: SHIP 0005 | G14: 45132 | H14: SHIP 0014 | I14: 4923872 | J14: IMPO
A15: 45062 | B15: 000000533 | C15: EASY POINT LOGISTICS SPA | D15: 256901.96 | E15: SHIP 0005 | G15: 45132 | H15: SHIP 0015 | I15: -154547 | J15: SALDO
C16: MENSAJERIA | D16: 17000 | I16: =SUM(I14:I15) -> 4769325
D17: =SUM(D12:D16) -> 2378211.8
A18: 45062 | B18: SHIP 0005 | C18: TRANSFERENCIA BANCARIA | D18: -2231607 | G18: 45156 | H18: SHIP 0021 | I18: 9319428 | J18: =I18-9054180 -> 265248
A19: 45069 | B19: VS SHIPS | C19: TRANSFERENCIA BANCARIA | D19: =-I5 -> -146606 | G19: 45156 | H19: SHIP 0014 | I19: -257891
D20: =SUM(D17:D19) -> -1.1645 | G20: 45156 | H20: SHIP 0016 | I20: -7359
I21: =SUM(I18:I20) -> 9054178
A22: 45065 | B22: 000957357 | C22: UPS DE CHILE LTDA | D22: 138124.49 | E22: SHIP 0008
A23: 45077 | B23: 000000564 | C23: EASY POINT LOGISTICS SPA | D23: 128637.81 | E23: SHIP 0008 | G23: 45182 | H23: SHIP 0021 | I23: 80084 | J23: SALDO
A24: 45079 | B24: 401959437-3 | C24: TESORERIA GENERAL DE LA REPUBLICA | D24: 569025.8 | E24: SHIP 0008 | G24: 45182 | H24: SHIP 0019 | I24: 135521 | J24: SALDO
D25: =SUM(D22:D24) -> 835788.1 | I25: =SUM(I23:I24) -> 215605
A26: 45064 | B26: SHIP 0008 | C26: TRANSFERENCIA BANCARIA | D26: -707150.49
A27: 45092 | B27: EASY POINT | C27: TRANSFERENCIA BANCARIA | D27: =-D23 -> -128637.81 | G27: 45191 | H27: SHIP 0023 | I27: 4102854
D28: =SUM(D25:D27) -> -0.1972 | G28: 45191 | H28: SHIP 0014 | I28: -257891 | J28: descontado doble
G29: 45191 | H29: SHIP 0016 | I29: -7359 | J29: descontado doble
A30: 45065 | B30: 000957358 | C30: UPS DE CHILE LTDA | D30: 138124.49 | E30: SHIP 0009 | G30: 45191 | H30: SHIP 0022 | I30: -94678 | J30: saldo mail 15/09
A31: 45077 | B31: 000000565 | C31: EASY POINT LOGISTICS SPA | D31: 128637.81 | E31: SHIP 0009 | I31: 3742926
A32: 45079 | B32: 401959436-5 | C32: TESORERIA GENERAL DE LA REPUBLICA | D32: 377120.1 | E32: SHIP 0009
D33: =SUM(D30:D32) -> 643882.4 | G33: 45191 | H33: SHIP 0014 | I33: =-I28 -> 257891 | J33: descontado doble
A34: 45064 | B34: SHIP 0009 | C34: TRANSFERENCIA BANCARIA | D34: -515244.49 | G34: 45191 | H34: SHIP 0016 | I34: =-I29 -> 7359 | J34: descontado doble
A35: 45092 | B35: EASY POINT | C35: TRANSFERENCIA BANCARIA | D35: =-D31 -> -128637.81 | G35: 45194 | H35: SHIP 0022 | I35: =-D223 -> -214199.52 | J35: saldo revisado c/ Caro 25/09
D36: =SUM(D33:D35) -> 0.1035 | G36: 45194 | H36: SHIP 0023 | I36: =-D236 -> -30501 | J36: ok mail 06/10
I37: =SUM(I33:I36) -> 20549.479
A38: 45071 | B38: 002883004 | C38: SERV AEROPORTUARIOS AEROSAN SA | D38: 120110.27 | E38: SHIP 0006 | G38: 45210 | H38: TRANSFERENCIA | I38: -20549.479
A39: 45071 | B39: 000005579 | C39: MOYA VARAS, MARINA | D39: 53550 | E39: SHIP 0006 | I39: =SUM(I37:I38) -> 0
A40: 45076 | B40: 000062153 | C40: ARANEDA MEZA, MARIO | D40: 152825.75 | E40: SHIP 0006
A41: 45076 | B41: 000062154 | C41: ARANEDA MEZA, MARIO | D41: 99028.23 | E41: SHIP 0006 | G41: 45260 | H41: SHIP 031 | I41: 260823 | J41: 952
A42: 45069 | B42: 000229152 | C42: MSL CHILE SA | D42: 47614.28 | E42: SHIP 0006 | G42: 45260 | H42: SHIP 034 | I42: 260823 | J42: 953
A43: 45069 | B43: 000052012 | C43: MSL CHILE SA | D43: 1000956 | E43: SHIP 0006 | G43: 45260 | H43: SHIP 035 | I43: 260823 | J43: 954
A44: 45069 | B44: 000000551 | C44: EASY POINT LOGISTICS SPA | D44: 257075.7 | E44: SHIP 0006 | G44: 45260 | H44: SHIP 036 | I44: 260823 | J44: 955
A45: 45070 | B45: 000000541 | C45: EASY POINT LOGISTICS SPA | D45: 51861.39 | E45: SHIP 0006 | G45: 45219 | H45: SHIP 0029 | I45: =-D286 -> -94375 | J45: SALDO
A46: 45085 | B46: 3670088217-3 | C46: TESORERIA GENERAL DE LA REPUBLICA | D46: 2264693 | E46: SHIP 0006 | G46: 45233 | H46: SHIP 0032 | I46: -50758.564 | J46: SALDO
A47: 45085 | B47: 3670088216-5 | C47: TESORERIA GENERAL DE LA REPUBLICA | D47: 882663.15 | E47: SHIP 0006 | G47: 45236 | H47: SHIP 0033 | I47: -4221.332 | J47: SALDO
D48: =SUM(D38:D47) -> 4930377.8 | I48: =SUM(I41:I47) -> 893937.1
A49: 45069 | B49: SHIP 0006 | C49: TRANSFERENCIA BANCARIA | D49: =-I6 -> -4904470
D50: =SUM(D48:D49) -> 25907.77
A51: 45112 | B51: COMPENSACIÓN | D51: =+D85 -> -25906.918
D52: =SUM(D50:D51) -> 0.8517
A54: 45071 | B54: 003527338 | C54: DHL EXPRESS (CHILE) LTDA | D54: 35453.67 | E54: SHIP 0011 | G54: SALDOS A FAVOR SIN USAR
A55: 45077 | B55: 000000566 | C55: EASY POINT LOGISTICS SPA | D55: 128637.81 | E55: SHIP 0011
A56: 45086 | B56: 0236665984 | C56: TESORERIA GENERAL DE LA REPUBLICA | D56: 174633.94 | E56: SHIP 0011
D57: =SUM(D54:D56) -> 338725.42
A58: 45075 | B58: SHIP 0011 | C58: TRANSFERENCIA BANCARIA | D58: -210087.67 | G58: GENERAL SALDOS
A59: 45092 | B59: EASY POINT | C59: TRANSFERENCIA BANCARIA | D59: =-D55 -> -128637.81 | H59: SHIP 0001 | I59: 0
D60: =SUM(D57:D59) -> -0.0552 | H60: SHIP 0002 | I60: 0
H61: SHIP 0003 | I61: 0
A62: 45076 | B62: 000959089 | C62: UPS DE CHILE LTDA | D62: 138124.49 | E62: SHIP 0012 | H62: SHIP 0004 | I62: =+D10 -> -0.4154
A63: 45077 | B63: 000000567 | C63: EASY POINT LOGISTICS SPA | D63: 128637.81 | E63: SHIP 0012 | H63: SHIP 0005 | I63: =+D20 -> -1.1645
A64: 45090 | B64: 401963068-K | C64: TESORERIA GENERAL DE LA REPUBLICA | D64: 546834.22 | E64: SHIP 0012 | H64: SHIP 0006 | I64: =+D52 -> 0.8517
D65: =SUM(D62:D64) -> 813596.52 | H65: SHIP 0007 | I65: =+D116 -> -0.3322
A66: 45075 | B66: SHIP 0012 | C66: TRANSFERENCIA BANCARIA | D66: -684958.49 | H66: SHIP 0008 | I66: =+D28 -> -0.1972
A67: 45092 | B67: EASY POINT | C67: TRANSFERENCIA BANCARIA | D67: =-D63 -> -128637.81 | H67: SHIP 0009 | I67: =+D36 -> 0.1035
D68: =SUM(D65:D67) -> 0.2152 | H68: SHIP 0010 | I68: =+D87 -> 0.8517
H69: SHIP 0011 | I69: =+D60 -> -0.0552
A70: 45082 | B70: 001280624 | C70: MAERSK LOGISTICS SPA | D70: 142438.24 | E70: SHIP 0010 | H70: SHIP 0012 | I70: =+D68 -> 0.2152
A71: 45082 | B71: 000170809 | C71: MAERSK LOGISTICS SPA | D71: 928925 | E71: SHIP 0010 | H71: SHIP 0013 | I71: =+D103 -> -1.5872
A72: 45085 | B72: 000000572 | C72: EASY POINT LOGISTICS SPA | D72: 261560.81 | E72: SHIP 0010 | H72: SHIP 0014 | I72: =+D158 -> 1.7301
A73: 45085 | B73: 000000579 | C73: EASY POINT LOGISTICS SPA | D73: 257474.35 | E73: SHIP 0010 | H73: SHIP 0015 | I73: =+D145 -> -110.5467
A74: 45086 | B74: 002885884 | C74: SERV AEROPORTUARIOS AEROSAN SA | D74: 345804.48 | E74: SHIP 0010 | H74: SHIP 0016 | I74: =+D174 -> -0.1016
A75: 45088 | B75: 000005627 | C75: MOYA VARAS, MARINA | D75: 47600 | E75: SHIP 0010 | H75: SHIP 0017 | I75: =+D124 -> -0.1214
A76: 45092 | B76: 000062404 | C76: ARANEDA MEZA, MARIO | D76: 293319.53 | E76: SHIP 0010 | H76: SHIP 0018 | I76: =+D132 -> 0.2283
A77: 45092 | B77: 000062405 | C77: ARANEDA MEZA, MARIO | D77: 152387.83 | E77: SHIP 0010 | H77: SHIP 0019 | I77: =+D190 -> 0.0337
A78: 45096 | B78: 000000607 | C78: EASY POINT LOGISTICS SPA | D78: 47204.92 | E78: SHIP 0010 | H78: SHIP 0020 | I78: =+D198 -> -0.5351
A79: 45096 | B79: 000002563 | C79: ARANEDA MEZA, MARIO | D79: -97758.5 | E79: SHIP 0010 | H79: SHIP 0021 | I79: =+D213 -> 0.1771
A80: 45099 | B80: 3670088462-1 | C80: TESORERIA GENERAL DE LA REPUBLICA | D80: 11654452 | E80: SHIP 0010 | H80: SHIP 0022 | I80: =+D224 -> 0
A81: 45099 | B81: 3670088467-2 | C81: TESORERIA GENERAL DE LA REPUBLICA | D81: 1624870.9 | E81: SHIP 0010 | G81: =D81-1251908 -> 372962.93 | H81: SHIP 0023 | I81: =+D237 -> 0.0484
D82: =SUM(D70:D81) -> 15658280 | H82: SHIP 0024 | I82: =+D277 -> -0.261
A83: 45086 | B83: SHIP 0010 | C83: TRANSFERENCIA BANCARIA | D83: -15513334 | E83: =14416063+1097271 -> 15513334 | H83: SHIP 0025 | I83: =+D245 -> 0.0968
A84: 45112 | B84: VS SHIPS | C84: TRANSFERENCIA BANCARIA | D84: =-I9 -> -170853 | H84: SHIP 0026 | I84: =+D253 -> 0.377
D85: =SUM(D82:D84) -> -25906.918 | H85: SHIP 0027 | I85: =+D261 -> 0.1738
A86: 45112 | B86: COMPENSACIÓN | D86: =+D50 -> 25907.77 | H86: SHIP 0028 | I86: =+D269 -> -0.1816
D87: =SUM(D85:D86) -> 0.8517 | H87: SHIP 0029 | I87: =+D287 -> 0.14
H88: SHIP 0030 | I88: =+D295 -> -0.0508
A89: 45089 | B89: 001283967 | C89: MAERSK LOGISTICS SPA | D89: 140515.2 | E89: SHIP 0013 | H89: SHIP 0031
A90: 45089 | B90: 000170849 | C90: MAERSK LOGISTICS SPA | D90: 1019093 | E90: SHIP 0013 | H90: SHIP 0032 | I90: =+D306 -> 0
A91: 45090 | B91: 000000587 | C91: EASY POINT LOGISTICS SPA | D91: 306620.16 | E91: SHIP 0013 | H91: SHIP 0033 | I91: =+D333 -> 0
A92: 45093 | B92: 000000616 | C92: EASY POINT LOGISTICS SPA | D92: 257558.84 | E92: SHIP 0013 | H92: SHIP 0034
A93: 45096 | B93: 002887605 | C93: SERV AEROPORTUARIOS AEROSAN SA | D93: 388815.84 | E93: SHIP 0013 | H93: SHIP 0035
A94: 45097 | B94: 000005653 | C94: MOYA VARAS, MARINA | D94: 51170 | E94: SHIP 0013 | H94: SHIP 0036
A95: 45099 | B95: 000000615 | C95: EASY POINT LOGISTICS SPA | D95: 47713.05 | E95: SHIP 0013 | H95: SHIP 0037
A96: 45104 | B96: 000062535 | C96: ARANEDA MEZA, MARIO | D96: 330177.4 | E96: SHIP 0013 | H96: SHIP 0038
A97: 45104 | B97: 000062536 | C97: ARANEDA MEZA, MARIO | D97: 54629.33 | E97: SHIP 0013 | H97: SHIP 0039
A98: 45108 | B98: 3670088511-3 | C98: TESORERIA GENERAL DE LA REPUBLICA | D98: 13335810 | E98: SHIP 0013 | H98: SHIP 0040
A99: 45108 | B99: 3670088536-9 | C99: TESORERIA GENERAL DE LA REPUBLICA | D99: 2011149.5 | E99: SHIP 0013 | H99: SHIP 0041
D100: =SUM(D89:D99) -> 17943252 | H100: SHIP 0042
A101: 45093 | B101: SHIP 0013 | C101: TRANSFERENCIA BANCARIA | D101: -17747397 | H101: SHIP 0043
...
