Workbook

Sheet Divisas
A2: FECHA | B2: DETALLE | C2: CLP | D2: TC | E2: USD | F2: SALDO | H2: FECHA | I2: DETALLE | J2: UYU | K2: TC | L2: USD | M2: SALDO
A3: 44966 | B3: COMISION | C3: -35318 | D3: =+D6 -> 825.6 | E3: =+C3/D3 -> -42.778585 | H3: 45134 | I3: INCIAL | J3: 833.38 | K3: 38 | L3: =+J3/K3 -> 21.931053 | M3: =+L3 -> 21.931053
A4: 44966 | B4: IVA | C4: -6710 | D4: =+D6 -> 825.6 | E4: =+C4/D4 -> -8.1274225 | H4: 45139 | I4: GTOS BCO | J4: -115 | K4: =+$K$3 -> 38 | L4: =+J4/K4 -> -3.0263158
A5: 44967 | B5: TRANSFERENCIA | C5: 43000 | D5: =+D6 -> 825.6 | E5: =+C5/D5 -> 52.083333 | H5: 45140 | I5: CO-1000 CAV | J5: -535.53 | K5: =+$K$3 -> 38 | L5: =+J5/K5 -> -14.092895
A6: 44984 | B6: COMPRA MC | C6: 82560 | D6: =+C6/E6 -> 825.6 | E6: 100 | H6: 45140 | I6: GTOS BCO | J6: -71.24 | K6: =+$K$3 -> 38 | L6: =+J6/K6 -> -1.8747368
A7: 44984 | B7: COMISION | C7: -35500 | D7: =+D6 -> 825.6 | E7: =+C7/D7 -> -42.999031 | H7: 45140 | I7: COMPRA MC | J7: 540000 | K7: =+J7/L7 -> 36.950009 | L7: 14614.34
A8: 44984 | B8: IVA | C8: -6745 | D8: =+D6 -> 825.6 | E8: =+C8/D8 -> -8.1698159 | F8: =SUM(E3:E8) -> 50.008479 | H8: 45141 | I8: CO-1000 CAV | J8: -111.61 | K8: =+$K$3 -> 38 | L8: =+J8/K8 -> -2.9371053
A9: 44994 | B9: COMPRA MC | C9: 2389500 | D9: =+C9/E9 -> 796.5 | E9: 3000 | H9: 45141 | I9: CO-1000 CAV | J9: =-284993.47-J8 -> -284881.86 | K9: =+$K$7 -> 36.950009 | L9: =+J9/K9 -> -7709.9266
A10: 44995 | B10: HOTEL DIRECTOR | C10: -41287 | D10: =+D6 -> 825.6 | E10: =+C10/D10 -> -50.008479 | H10: 45141 | I10: GTOS BCO | J10: -71.93 | K10: =+$K$7 -> 36.950009 | L10: =+J10/K10 -> -1.9466842
A11: 44995 | B11: HOTEL DIRECTOR | C11: =-2382380-C10 -> -2341093 | D11: =+D9 -> 796.5 | E11: =+C11/D11 -> -2939.2254 | H11: 45141 | I11: CO-1000 CAV | J11: -250000 | K11: =+$K$7 -> 36.950009 | L11: =+J11/K11 -> -6765.8981
A12: 45007 | B12: COMPRA MC | C12: 4903002 | D12: =+C12/E12 -> 819.9 | E12: 5980 | H12: 45141 | I12: GTOS BCO | J12: -71.93 | K12: =+$K$7 -> 36.950009 | L12: =+J12/K12 -> -1.9466842
A13: 45008 | B13: RSM | C13: -48407 | D13: =+D9 -> 796.5 | E13: =+C13/D13 -> -60.774639 | H13: 45149 | I13: RSM | J13: -1600 | K13: =+$K$7 -> 36.950009 | L13: =+J13/K13 -> -43.301748 | M13: =+M3+SUM(L4:L13) -> 91.320139
A14: 45008 | B14: RSM | C14: =-4588931-C13 -> -4540524 | D14: =+D12 -> 819.9 | E14: =+C14/D14 -> -5537.8997 | F14: =+F8+SUM(E9:E14) -> 442.10026 | H14: 45170 | I14: COMPRA MC | J14: 7370 | K14: =+J14/L14 -> 36.85 | L14: 200
A15: 45027 | B15: COMPRA MC | C15: 150000000 | D15: =+C15/E15 -> 809.49999 | E15: 185299.57 | H15: 45170 | I15: GTOS BCO | J15: -115 | K15: =+$K$7 -> 36.950009 | L15: =+J15/K15 -> -3.1123131
A16: 45028 | B16: SONDA | C16: -362478 | D16: =+D12 -> 819.9 | E16: =+C16/D16 -> -442.10026 | H16: 45173 | I16: CO-1000 CAV | J16: -3259.28 | K16: =+$K$7 -> 36.950009 | L16: =+J16/K16 -> -88.207826
A17: 45028 | B17: SONDA | C17: =-148351856-C16 -> -147989378 | D17: =+D15 -> 809.49999 | E17: =+C17/D17 -> -182815.79 | H17: 45173 | I17: CO-1000 CAV | J17: =-7022.06-J16 -> -3762.78 | K17: =+$K$14 -> 36.85 | L17: =+J17/K17 -> -102.11072
A18: 45028 | B18: COMPRA MC | C18: 149145000 | D18: =+C18/E18 -> 815 | E18: 183000 | H18: 45173 | I18: GTOS BCO | J18: -71.08 | K18: =+$K$14 -> 36.85 | L18: =+J18/K18 -> -1.9289009
A19: 45029 | B19: KOLFF | C19: -2010622 | D19: =+D15 -> 809.49999 | E19: =+C19/D19 -> -2483.7826 | H19: 45180 | I19: VISA DEBITO | J19: -1334.1 | K19: =+$K$14 -> 36.85 | L19: =+J19/K19 -> -36.203528 | M19: =+M13+SUM(L14:L19) -> 59.756852
A20: 45029 | B20: KOLFF | C20: =-27660783-C19 -> -25650161 | D20: =+$D$18 -> 815 | E20: =+C20/D20 -> -31472.59 | H20: 45200 | I20: GTOS BCO | J20: -115 | K20: =+$K$14 -> 36.85 | L20: =+J20/K20 -> -3.1207598 | M20: =+M19+L20 -> 56.636092
A21: 45033 | B21: RSM | C21: -948492 | D21: =+$D$18 -> 815 | E21: =+C21/D21 -> -1163.7939 | H21: 45231 | I21: GTOS BCO | J21: -115 | K21: =+$K$14 -> 36.85 | L21: =+J21/K21 -> -3.1207598
A22: 45033 | B22: FEDEX | C22: -522269 | D22: =+$D$18 -> 815 | E22: =+C22/D22 -> -640.82086 | H22: 45257 | I22: GTOS BCO | J22: -1613.55 | K22: =+$K$14 -> 36.85 | L22: =+J22/K22 -> -43.786974 | M22: =+M20+SUM(L21:L22) -> 9.7283582
A23: 45033 | B23: SII - IVA | C23: -66627802 | D23: =+$D$18 -> 815 | E23: =+C23/D23 -> -81751.904 | H23: 45261 | I23: GTOS BCO | J23: -115 | K23: =+$K$14 -> 36.85 | L23: =+J23/K23 -> -3.1207598 | M23: =+M22+L23 -> 6.6075984
A24: 45034 | B24: COMISION | C24: -88930 | D24: =+$D$18 -> 815 | E24: =+C24/D24 -> -109.11656 | H24: 45292 | I24: GTOS BCO | J24: -115 | K24: =+$K$14 -> 36.85 | L24: =+J24/K24 -> -3.1207598 | M24: =+M23+L24 -> 3.4868385
A25: 45034 | B25: IVA | C25: -16897 | D25: =+$D$18 -> 815 | E25: =+C25/D25 -> -20.732515 | K25: =+$K$14 -> 36.85 | L25: =+J25/K25 -> 0
A26: 45035 | B26: UPS | C26: -406965 | D26: =+$D$18 -> 815 | E26: =+C26/D26 -> -499.34356 | K26: =+$K$14 -> 36.85 | L26: =+J26/K26 -> 0
A27: 45041 | B27: COMISION | C27: -107629 | D27: =+D18 -> 815 | E27: =+C27/D27 -> -132.06012 | K27: =+$K$14 -> 36.85 | L27: =+J27/K27 -> 0
A28: 45041 | B28: COMISION | C28: -107629 | D28: =+D18 -> 815 | E28: =+C28/D28 -> -132.06012 | F28: =+F14+SUM(E15:E28) -> 67077.578 | K28: =+$K$14 -> 36.85 | L28: =+J28/K28 -> 0
A29: 45051 | B29: C-01523 ADUANA | C29: -1926369 | D29: =+D18 -> 815 | E29: =+C29/D29 -> -2363.6429 | K29: =+$K$14 -> 36.85 | L29: =+J29/K29 -> 0
A30: 45055 | B30: COMISION | C30: =-1432-89662 -> -91094 | D30: =+$D$18 -> 815 | E30: =+C30/D30 -> -111.77178 | K30: =+$K$14 -> 36.85 | L30: =+J30/K30 -> 0
A31: 45055 | B31: IVA | C31: =-272-17036 -> -17308 | D31: =+$D$18 -> 815 | E31: =+C31/D31 -> -21.23681 | K31: =+$K$14 -> 36.85 | L31: =+J31/K31 -> 0
A32: 45062 | B32: RSM | C32: -2303790 | D32: =+D23 -> 815 | E32: =+C32/D32 -> -2826.7362
A33: 45062 | B33: SHIP 0005 | C33: -2231607 | D33: =+D23 -> 815 | E33: =+C33/D33 -> -2738.1681
A34: 45064 | B34: UPS | C34: -707150 | D34: =+D23 -> 815 | E34: =+C34/D34 -> -867.66871 | J34: =SUM(J3:J33) -> 128.49 | L34: =SUM(L3:L33) -> 3.4868385
A35: 45064 | B35: UPS | C35: -515245 | D35: =+$D$18 -> 815 | E35: =+C35/D35 -> -632.20245
A36: 45069 | B36: SHIP 0006 | C36: -5093663 | D36: =+$D$18 -> 815 | E36: =+C36/D36 -> -6249.8933 | L36: 4813.69 | M36: TOTAL USD
A37: 45075 | B37: DHL | C37: -210088 | D37: =+$D$18 -> 815 | E37: =+C37/D37 -> -257.77669
A38: 45075 | B38: UPS | C38: -684959 | D38: =+$D$18 -> 815 | E38: =+C38/D38 -> -840.44049 | F38: =+F28+SUM(E29:E38) -> 50168.04 | L38: =SUM(L34:L36) -> 4817.1768
A39: 45084 | B39: SHIP 010 | C39: -1097271 | D39: =+$D$18 -> 815 | E39: =+C39/D39 -> -1346.3448
A40: 45086 | B40: SHIP 010 | C40: =-(7000000*2+416063) -> -14416063 | D40: =+$D$18 -> 815 | E40: =+C40/D40 -> -17688.421
A41: 45092 | B41: SHIP 013 | C41: -1159608 | D41: =+$D$18 -> 815 | E41: =+C41/D41 -> -1422.8319
A42: 45092 | B42: RSM | C42: -730449 | D42: =+$D$18 -> 815 | E42: =+C42/D42 -> -896.25644
A43: 45092 | B43: EASY POINT | C43: -514552 | D43: =+$D$18 -> 815 | E43: =+C43/D43 -> -631.35215
A44: 45093 | B44: DEPARTAMENTO | C44: -367096 | D44: =+$D$18 -> 815 | E44: =+C44/D44 -> -450.42454
A45: 45093 | B45: SHIP 013 | C45: =-7000000*2-2587789 -> -16587789 | D45: =+$D$18 -> 815 | E45: =+C45/D45 -> -20353.115
A46: 45093 | B46: ALQUILER AUTO | C46: -1330000 | D46: =+$D$18 -> 815 | E46: =+C46/D46 -> -1631.9018
A47: 45096 | B47: DEPARTAMENTO | C47: -367096 | D47: =+$D$18 -> 815 | E47: =+C47/D47 -> -450.42454
A48: 45096 | B48: GASTOS PAGO BELDEN | C48: -119717 | D48: =+$D$18 -> 815 | E48: =+C48/D48 -> -146.89202
A49: 45104 | B49: COMPRA MC | C49: 15961000 | D49: =+C49/E49 -> 798.05 | E49: 20000
A50: 45104 | B50: SHIP 007 | C50: -4197312 | D50: =+$D$18 -> 815 | E50: =+C50/D50 -> -5150.0761
A51: 45104 | B51: SHIP 007 | C51: =-(7000000+1323420)-C50 -> -4126108 | D51: =+$D$49 -> 798.05 | E51: =+C51/D51 -> -5170.2375
A52: 45106 | B52: DEPARTAMENTO | C52: -1399894 | D52: =+$D$49 -> 798.05 | E52: =+C52/D52 -> -1754.1432 | F52: =+F38+SUM(E39:E52) -> 13075.619
A53: 45112 | B53: DIF VS SHIPS | C53: -182337 | D53: =+$D$49 -> 798.05 | E53: =+C53/D53 -> -228.47817
A54: 45117 | B54: GASTOS PAGO BELDEN | C54: -121398 | D54: =+$D$49 -> 798.05 | E54: =+C54/D54 -> -152.11829
A55: 45117 | B55: SHIP 015 | C55: -6760300 | D55: =+$D$49 -> 798.05 | E55: =+C55/D55 -> -8471.0231
A56: 45117 | B56: SHIP 017 | C56: -265087 | D56: =+$D$49 -> 798.05 | E56: =+C56/D56 -> -332.16841
A57: 45124 | B57: SHIP 018 | C57: -232541 | D57: =+$D$49 -> 798.05 | E57: =+C57/D57 -> -291.3865
A58: 45124 | B58: EASY POINT | C58: -128845 | D58: =+$D$49 -> 798.05 | E58: =+C58/D58 -> -161.44978
A59: 45124 | B59: RSM | C59: -721494 | D59: =+$D$49 -> 798.05 | E59: =+C59/D59 -> -904.07117
A60: 45126 | B60: ROTULADORA | C60: -265965 | D60: =+$D$49 -> 798.05 | E60: =+C60/D60 -> -333.26859
A61: 45126 | B61: ALQUILER AUTO | C61: -600000 | D61: =+$D$49 -> 798.05 | E61: =+C61/D61 -> -751.83259
A62: 45126 | B62: PATENTES | C62: -265824 | D62: =+$D$49 -> 798.05 | E62: =+C62/D62 -> -333.09191
A63: 45128 | B63: ROTULADORA | C63: -252000 | D63: =+$D$49 -> 798.05 | E63: =+C63/D63 -> -315.76969
A64: 45132 | B64: COMPRA MC | C64: 10341250 | D64: =+C64/E64 -> 827.3 | E64: 12500
A65: 45132 | B65: SHIP 014 | C65: -639207 | D65: =+$D$49 -> 798.05 | E65: =+C65/D65 -> -800.96109
A66: 45132 | B66: SHIP 014 | C66: =-4769216-C65 -> -4130009 | D66: =+$D$64 -> 827.3 | E66: =+C66/D66 -> -4992.154
A67: 45132 | B67: SHIP 016 | C67: -2468935 | D67: =+$D$64 -> 827.3 | E67: =+C67/D67 -> -2984.3285
A68: 45134 | B68: ALQUILER AUTO | C68: -1000000 | D68: =+$D$64 -> 827.3 | E68: =+C68/D68 -> -1208.7514
A69: 45134 | B69: DEPARTAMENTO | C69: -932000 | D69: =+$D$64 -> 827.3 | E69: =+C69/D69 -> -1126.5563
A70: 45134 | B70: SHIP 018 | C70: -128795 | D70: =+$D$64 -> 827.3 | E70: =+C70/D70 -> -155.68113 | F70: =+F52+SUM(E53:E70) -> 2032.5287
A71: 45140 | B71: GASTOS PAGO BELDEN | C71: -127211 | D71: =+$D$64 -> 827.3 | E71: =+C71/D71 -> -153.76647
A72: 45141 | B72: COMPRA MC | C72: 17949750 | D72: =+C72/E72 -> 854.75 | E72: 21000
A73: 45141 | B73: SHIP 019 | C73: -1554300 | D73: =+$D$64 -> 827.3 | E73: =+C73/D73 -> -1878.7622
A74: 45141 | B74: SHIP 019 | C74: =-7000000*2-3588890-C73 -> -16034590 | D74: =+$D$72 -> 854.75 | E74: =+C74/D74 -> -18759.392
A75: 45146 | B75: SHIP 020 | C75: -605489 | D75: =+$D$72 -> 854.75 | E75: =+C75/D75 -> -708.3814
A76: 45146 | B76: RSM | C76: -756621 | D76: =+$D$72 -> 854.75 | E76: =+C76/D76 -> -885.19567
A77: 45149 | B77: COMPRA MC | C77: 11085750 | D77: =+C77/E77 -> 852.75 | E77: 13000
A78: 45149 | B78: KOLFF | C78: -553050 | D78: =+$D$72 -> 854.75 | E78: =+C78/D78 -> -647.0313
A79: 45149 | B79: KOLFF | C79: =-2500000-8356457-C78 -> -10303407 | D79: =+$D$77 -> 852.75 | E79: =+C79/D79 -> -12082.565
A80: 45154 | B80: RITTAL CL | C80: -275221 | D80: =+$D$77 -> 852.75 | E80: =+C80/D80 -> -322.74524
A81: 45156 | B81: COMPRA MC | C81: 9532050 | D81: =+C81/E81 -> 866.55 | E81: 11000
A82: 45156 | B82: SHIP 021 | C82: -507122 | D82: =+$D$77 -> 852.75 | E82: =+C82/D82 -> -594.69012
A83: 45156 | B83: SHIP 021 | C83: =-(2054180+7000000)-C82 -> -8547058 | D83: =+$D$81 -> 866.55 | E83: =+C83/D83 -> -9863.3178
A84: 45156 | B84: ALQUILER AUTO | C84: -250000 | D84: =+$D$81 -> 866.55 | E84: =+C84/D84 -> -288.50038
A85: 45162 | B85: DEPARTAMENTO | C85: -456000 | D85: =+$D$81 -> 866.55 | E85: =+C85/D85 -> -526.22468
A86: 45167 | B86: EASY POINT | C86: -128753 | D86: =+$D$81 -> 866.55 | E86: =+C86/D86 -> -148.58116
A87: 45168 | B87: COMPRA MC | C87: 3314220 | D87: =+C87/E87 -> 849.8 | E87: 3900
A88: 45168 | B88: ALQUILER AUTO | C88: -150239 | D88: =+$D$81 -> 866.55 | E88: =+C88/D88 -> -173.37603
A89: 45168 | B89: ALQUILER AUTO | C89: =-550000-C88 -> -399761 | D89: =+$D$87 -> 849.8 | E89: =+C89/D89 -> -470.41775 | F89: =+F70+SUM(E71:E89) -> 3429.5823
A90: 45170 | B90: COMPRA MC | C90: 3228100 | D90: =+C90/E90 -> 849.5 | E90: 3800
A91: 45170 | B91: SHIP 022 | C91: -1926048 | D91: =+$D$87 -> 849.8 | E91: =+C91/D91 -> -2266.4721
A92: 45170 | B92: SYNIXTOR | C92: -988411 | D92: =+$D$87 -> 849.8 | E92: =+C92/D92 -> -1163.1101
A93: 45170 | B93: SYNIXTOR | C93: =-2369683-C92 -> -1381272 | D93: =+$D$90 -> 849.5 | E93: =+C93/D93 -> -1625.9823
A94: 45170 | B94: VDA | C94: -230800 | D94: =+$D$90 -> 849.5 | E94: =+C94/D94 -> -271.68923
A95: 45170 | B95: DEPARTAMENTO | C95: -1074000 | D95: =+$D$90 -> 849.5 | E95: =+C95/D95 -> -1264.2731
A96: 45177 | B96: VDA | C96: -200024 | D96: =+$D$90 -> 849.5 | E96: =+C96/D96 -> -235.46086
A97: 45177 | B97: COMISION | C97: =-72270-723 -> -72993 | D97: =+$D$90 -> 849.5 | E97: =+C97/D97 -> -85.924662
A98: 45177 | B98: IVA | C98: =-13731-137 -> -13868 | D98: =+$D$90 -> 849.5 | E98: =+C98/D98 -> -16.324897
A99: 45182 | B99: SHIP 021 + 019 | C99: -215605 | D99: =+$D$90 -> 849.5 | E99: =+C99/D99 -> -253.80224
A100: 45189 | B100: COMPRA MC | C100: 966405 | D100: =+C100/E100 -> 878.55 | E100: 1100
A101: 45189 | B101: HOTEL EUROTEL | C101: -39538 | D101: =+$D$90 -> 849.5 | E101: =+C101/D101 -> -46.542672
...

Sheet Mensuales
B2: CHILE | E2: URUGUAY
B3: USD | C3: CLP | D3: TOTAL | E3: USD | F3: UYU | G3: TOTAL
A4: *FEBRERO 23 | B4: 50099.5 | C4: =+Divisas!F8 -> 50.008479 | D4: =SUM(B4:C4) -> 50149.508 | E4: 47948.64 | F4: =+Divisas!M3 -> 21.931053 | G4: =SUM(E4:F4) -> 47970.571
A5: *MARZO 23 | B5: 83412.26 | C5: =+Divisas!F14 -> 442.10026 | D5: =SUM(B5:C5) -> 83854.36 | E5: 14178.96 | F5: =+Divisas!M3 -> 21.931053 | G5: =SUM(E5:F5) -> 14200.891
A6: *ABRIL 23 | B6: 177276 | C6: =+Divisas!F28 -> 67077.578 | D6: =SUM(B6:C6) -> 244353.58 | E6: 65430.66 | F6: =+Divisas!M3 -> 21.931053 | G6: =SUM(E6:F6) -> 65452.591
A7: *MAYO 23 | B7: 177276 | C7: =+Divisas!F38 -> 50168.04 | D7: =SUM(B7:C7) -> 227444.04 | E7: 35722.54 | F7: =+Divisas!M3 -> 21.931053 | G7: =SUM(E7:F7) -> 35744.471
A8: *JUNIO 23 | B8: 156081 | C8: =+Divisas!F52 -> 13075.619 | D8: =SUM(B8:C8) -> 169156.62 | E8: 30885.39 | F8: =+Divisas!M3 -> 21.931053 | G8: =SUM(E8:F8) -> 30907.321
A9: *JULIO 23 | B9: 137697 | C9: =+Divisas!F70 -> 2032.5287 | D9: =SUM(B9:C9) -> 139729.53 | E9: 11033.86 | F9: =+Divisas!M3 -> 21.931053 | G9: =SUM(E9:F9) -> 11055.791
A10: *AGOSTO 23 | B10: 53797 | C10: =+Divisas!F89 -> 3429.5823 | D10: =SUM(B10:C10) -> 57226.582 | E10: 9097.25 | F10: =+Divisas!M13 -> 91.320139 | G10: =SUM(E10:F10) -> 9188.5701
A11: *SEPTIEMBRE 23 | B11: 38897.15 | C11: =+Divisas!F108 -> 621.37102 | D11: =SUM(B11:C11) -> 39518.521 | E11: 23059.25 | F11: =+Divisas!M19 -> 59.756852 | G11: =SUM(E11:F11) -> 23119.007
A12: *OCTUBRE 23 | B12: 610701.1 | C12: =+Divisas!F140 -> 176.82873 | D12: =SUM(B12:C12) -> 610877.93 | E12: 34914.92 | F12: =+Divisas!M20 -> 56.636092 | G12: =SUM(E12:F12) -> 34971.556
A13: *NOVIEMBRE 23 | B13: 488531.3 | C13: =+Divisas!F177 -> 1097.504 | D13: =SUM(B13:C13) -> 489628.8 | E13: 14232.28 | F13: =+Divisas!M22 -> 9.7283582 | G13: =SUM(E13:F13) -> 14242.008
A14: *DICIEMBRE 23 | B14: 189563.43 | C14: =+Divisas!F199 -> 641.85083 | D14: =SUM(B14:C14) -> 190205.28 | E14: 8729.42 | F14: =+Divisas!M23 -> 6.6075984 | G14: =SUM(E14:F14) -> 8736.0276
A15: *ENERO 24 | B15: 78397.63 | C15: =+Divisas!F220 -> 229.98708 | D15: =SUM(B15:C15) -> 78627.617 | E15: 2862.98 | F15: =+Divisas!M24 -> 3.4868385 | G15: =SUM(E15:F15) -> 2866.4668
A16: *FEBRERO 24 | B16: 78397.63 | C16: =+Divisas!F221 -> 137.26529 | D16: =SUM(B16:C16) -> 78534.895 | E16: 2601.8 | F16: =+Divisas!M24 -> 3.4868385 | G16: =SUM(E16:F16) -> 2605.2868
