Workbook

Sheet CUADRATURA 31.12.2023
A1: Planilla Unificada
A2: Tipo Factura Recibida | E2: Cant.Reg | F2: Exento | G2: Neto | H2: I.V.A. | I2: Otros Imp. | J2: I.V.A. No Rec | K2: Total | L2: Total Ventas
A3: 33 | B3: Factura de Venta Electrónica | E3: =COUNTIF('Planilla unificada'!$B:$B,A3) -> 1 | F3: =SUMIFS('Planilla unificada'!$H:$H,'Planilla unificada'!$B:$B,'CUADRATURA 31.12.2023'!A3) -> 0 | G3: =SUMIFS('Planilla unificada'!$I:$I,'Planilla unificada'!$B:$B,'CUADRATURA 31.12.2023'!A3) -> 28439112 | H3: =SUMIFS('Planilla unificada'!$J:$J,'Planilla unificada'!$B:$B,'CUADRATURA 31.12.2023'!A3) -> 5403431 | K3: =SUM(F3:J3) -> 33842543
L4: =SUM(K3) -> 33842543
E5: =SUM(E3:E4) -> 1 | F5: =SUM(F3:F4) -> 0 | G5: =SUM(G3:G4) -> 28439112 | H5: =SUM(H3:H4) -> 5403431 | I5: =SUM(I3:I4) -> 0 | J5: =SUM(J3:J4) -> 0
K6: =SUM(F5:J5) -> 33842543 | L6: =L4-K6 -> 0
A8: MAGNUS
A9: Tipo Factura Recibida | E9: Cant.Reg | F9: Exento | G9: Neto | H9: I.V.A. | I9: Otros Imp. | J9: I.V.A. No Rec | K9: Total | L9: Total Ventas
A10: 33 | B10: Factura de Venta Electrónica | E10: =COUNTIF('MAGNUS LV'!$A:$A,B10) -> 1 | F10: =SUMIFS('MAGNUS LV'!$J:$J,'MAGNUS LV'!$A:$A,'CUADRATURA 31.12.2023'!B10) -> 0 | G10: =SUMIFS('MAGNUS LV'!$G:$G,'MAGNUS LV'!$A:$A,'CUADRATURA 31.12.2023'!B10) -> 28439112 | H10: =SUMIFS('MAGNUS LV'!$H:$H,'MAGNUS LV'!$A:$A,'CUADRATURA 31.12.2023'!B10) -> 5403431 | K10: =SUM(F10:J10) -> 33842543
L11: =SUM(K10) -> 33842543
E12: =SUM(E10:E11) -> 1 | F12: =SUM(F10:F11) -> 0 | G12: =SUM(G10:G11) -> 28439112 | H12: =SUM(H10:H11) -> 5403431 | I12: =SUM(I10:I11) -> 0 | J12: =SUM(J10:J11) -> 0
K13: =SUM(F12:J12) -> 33842543 | L13: =L11-K13 -> 0

Sheet MAGNUS LV
A1: Libro de Ventas
A2: Empresa :PROYESCO CHILE SPA / Periodo : 01/12/23 al 31/12/23
A3: Tipo.Doc. | B3: Numero | C3: Fecha | D3: Titulares | F3: R.U.T. | G3: Afecto | H3: I.V.A. | J3: Exento | K3: Otros Imp. | L3: Total
A4: Factura de Venta Electrónica | B4: 3 | C4: 45280 | D4: TECHINT CHILE SA | F4: 914260000 | G4: 28439112 | H4: 5403431 | L4: 33842543

Sheet Planilla unificada
A1: Nro | B1: Tipo Doc | C1: Tipo Venta | D1: Rut cliente | E1: Razon Social | F1: Folio | G1: Fecha Docto | H1: Monto Exento | I1: Monto Neto | J1: Monto IVA | K1: Monto total | L1: Glosa documento/descripcion gasto o servicio | M1: Numero cta Magnus | N1: Nombre Cuenta | O1: RESPALDO PDF | P1: Ø Documentado | Q1: Օ Sin Documento
A2: 1 | B2: 33 | C2: Del Giro | D2: 91426000-0 | E2: TECHINT CHILE S.A. | F2: 3 | G2: 45280 | H2: 0 | I2: 28439112 | J2: 5403431 | K2: 33842543 | L2: PO N°4500438352 REV 2 Dated 05.09.2023 segunda cuota con liberación parcial Fase I:TS YTRS. MIGO 5003632137 80 Gabinetes/equipos (trs) USD 13774.77 90 Gabinetes/equipos (ts) USD 19170.23 | M2: 60102004 | N2: GENERICO CON IVA | O2: Ø Documentado

Sheet 01-31
A1: Nro | B1: Tipo Doc | C1: Tipo Venta | D1: Rut cliente | E1: Razon Social | F1: Folio | G1: Fecha Docto | H1: Monto Exento | I1: Monto Neto | J1: Monto IVA | K1: Monto total | L1: Glosa documento/descripcion gasto o servicio | M1: Numero cta Magnus | N1: Nombre Cuenta | O1: RESPALDO PDF | P1: Ø Documentado | Q1: Օ Sin Documento
A2: 1 | B2: 33 | C2: Del Giro | D2: 91426000-0 | E2: TECHINT CHILE S.A. | F2: 3 | G2: 45280 | H2: 0 | I2: 28439112 | J2: 5403431 | K2: 33842543 | L2: PO N°4500438352 REV 2 Dated 05.09.2023 segunda cuota con liberación parcial Fase I:TS YTRS. MIGO 5003632137 80 Gabinetes/equipos (trs) USD 13774.77 90 Gabinetes/equipos (ts) USD 19170.23 | M2: 60102004 | N2: GENERICO CON IVA | O2: Ø Documentado

Sheet Titulares
A1: Titular | B1: Nombre Titular | C1: NUMERO CTA | D1: NOMBRE DE CTA
A2: 91426000-0 | B2: TECHINT CHILE S.A. | C2: 60102004 | D2: GENERICO CON IVA

Sheet 31.12.2023 LV
A1: Nro | B1: Tipo Doc | C1: Tipo Venta | D1: Rut cliente | E1: Razon Social | F1: Folio | G1: Fecha Docto | H1: Fecha Recepcion | I1: Fecha Acuse Recibo | J1: Fecha Reclamo | K1: Monto Exento | L1: Monto Neto | M1: Monto IVA | N1: Monto total | O1: IVA Retenido Total | P1: IVA Retenido Parcial | Q1: IVA no retenido | R1: IVA propio | S1: IVA Terceros | T1: RUT Emisor Liquid. Factura | U1: Neto Comision Liquid. Factura | V1: Exento Comision Liquid. Factura | W1: IVA Comision Liquid. Factura | X1: IVA fuera de plazo | Y1: Tipo Docto. Referencia | Z1: Folio Docto. Referencia | AA1: Num. Ident. Receptor Extranjero | AB1: Nacionalidad Receptor Extranjero | AC1: Credito empresa constructora | AD1: Impto. Zona Franca (Ley 18211) | AE1: Garantia Dep. Envases | AF1: Indicador Venta sin Costo | AG1: Indicador Servicio Periodico | AH1: Monto No facturable | AI1: Total Monto Periodo | AJ1: Venta Pasajes Transporte Nacional | AK1: Venta Pasajes Transporte Internacional | AL1: Numero Interno | AM1: Codigo Sucursal | AN1: NCE o NDE sobre Fact. de Compra | AO1: Codigo Otro Imp. | AP1: Valor Otro Imp. | AQ1: Tasa Otro Imp.
A2: 1 | B2: 33 | C2: Del Giro | D2: 91426000-0 | E2: TECHINT CHILE S.A. | F2: 3 | G2: 45280 | H2: 45280.424 | J2: 45288.671 | K2: 0 | L2: 28439112 | M2: 5403431 | N2: 33842543 | O2: 0 | P2: 0 | Q2: 0 | R2: 0 | S2: 0 | T2: - | U2: 0 | V2: 0 | W2: 0 | X2: 0 | Y2: 0 | AC2: 0 | AE2: 0 | AF2: 2 | AG2: 0 | AH2: 0 | AI2: 0 | AM2: 88308397
