Workbook

Sheet 02.2026
A1: razon social rut | B1: mes | C1: rut | D1: nombre | E1: apellido paterno | F1: apellido materno | G1: cargo | H1: fecha contratacion | I1: contrato hasta | J1: afp nombre | K1: prevision nombre | L1: isapre monto pactado | M1: Días Trabajados | N1: Sueldo Base | O1: Gratificación Mensual | P1: Renta Imponible | Q1: Suma de Haberes | R1: AFP | S1: Salud 7% (Fonasa) | T1: Suma Descuentos Legales, Impuestos y Por planilla | U1: Liquido a Pago | V1: Seguro accidentes del Trabajo | W1: Seguro Cesantia Empleador | X1: Seguro Cesantia (Fondo Solidario) | Y1: Seguro Invalidez y Supervivencia (SIS) | Z1: Capitalización Individual AFP | AA1: Expectativa de Vida | AB1: Costo Empresa
A2: 77656064-2 | B2: 2 | C2: 44606242-5 | D2: CHRISTIAN ROLANDO | E2: SAINT | F2: GERMAIN | G2: Supervisor de Comunicaciones | H2: 15/02/2026 | I2: 30/11/2026 | J2: Uno | K2: Fonasa | M2: 14 | N2: 326667 | O2: 81667 | P2: 408334 | Q2: 408334 | R2: 42712 | S2: 28583 | T2: 71295 | U2: 337039 | V2: 3798 | W2: 11433 | X2: 817 | Y2: 6288 | Z2: 408 | AA2: 3675 | AB2: 434753
A3: 77656064-2 | B3: 2 | C3: 44606258-1 | D3: GALO ANDRES | E3: TOBAR | F3: CISNEROS | G3: Supervisor de Comunicaciones | H3: 15/02/2026 | I3: 30/11/2026 | J3: Uno | K3: Fonasa | M3: 14 | N3: 326667 | O3: 81667 | P3: 408334 | Q3: 408334 | R3: 42712 | S3: 28583 | T3: 71295 | U3: 337039 | V3: 3798 | W3: 11433 | X3: 817 | Y3: 6288 | Z3: 408 | AA3: 3675 | AB3: 434753
N5: =+SUM(N2:N3) -> 653334 | O5: =+SUM(O2:O3) -> 163334 | P5: =+SUM(P2:P3) -> 816668 | Q5: =+SUM(Q2:Q3) -> 816668 | R5: =+SUM(R2:R3) -> 85424 | S5: =+SUM(S2:S3) -> 57166 | T5: =+SUM(T2:T3) -> 142590 | U5: =+SUM(U2:U3) -> 674078 | ... AB5: =+SUM(AB2:AB3) -> 869506
T13: =+R5+S5+V5+W5+X5+Y5+Z5+AA5 -> 195428

Sheet Centralizacion
C2: CENTRALIZACION PROYESCO
C3: FEBRERO 2025
B4: Cuentas | D4: D E B E | E4: H A B E R
C6: REMUNERACIONES | D6: =+'02.2026'!N5+'02.2026'!O5 -> 816668
C7: LEYES SOCIALES | D7: =+'02.2026'!AA5+'02.2026'!Z5+'02.2026'!Y5+'02.2026'!X5+'02.2026'!W5+'02.2026'!V5 -> 52838
C8: IMPUESTO UNICO A LOS TRABAJADORES | E8: 0
C9: IMPUESTO RELIQUIDADO
C10: PREVIRED POR PAGAR | E10: =+'02.2026'!R5+'02.2026'!S5+'02.2026'!V5+'02.2026'!W5+'02.2026'!X5+'02.2026'!Y5+'02.2026'!Z5+'02.2026'!AA5 -> 195428 | F10: 195428 | G10: =+E10-F10 -> 0
C11: ANTICIPO DE SUELDO
C12: SUELDOS POR PAGAR | E12: =+'02.2026'!$U$5 -> 674078
D15: =SUM(D6:D14) -> 869506 | E15: =SUM(E6:E14) -> 869506 | G15: =+'02.2026'!$AB$5 -> 869506
D16: =D15-G15 -> 0 | E16: =E15-G15 -> 0
C21: CENTRALIZACION FINIQUITO
C22: FEBRERO 2025
B24: Cuentas | D24: D E B E | E24: H A B E R
C26: FINIQUITOS | D26: 0
C27: FINIQUITOS POR PAGAR | E27: 0 | K27: =SUM(K24:K26) -> 0
D30: =SUM(D26:D29) -> 0 | E30: =SUM(E26:E29) -> 0
