Workbook

Sheet 03.2026
A1: razon social rut | B1: mes | C1: rut | D1: nombre | E1: apellido paterno | F1: apellido materno | G1: centro costo nombre | H1: cargo | I1: afp nombre | J1: prevision nombre | K1: isapre monto pactado | L1: tipo contrato | M1: fecha contratacion | N1: contrato hasta | O1: Días Trabajados | P1: Días Ausencia | Q1: Dias Vacaciones Mes | R1: Días Licencia | S1: Sueldo Base | T1: Gratificación Mensual | U1: Suma de Haberes Afectos | V1: Suma de Haberes | W1: AFP | X1: Fonasa | Y1: Suma de Leyes Sociales | Z1: Impuestos | AA1: Suma Descuentos Legales, Impuestos y Por planilla | AB1: Liquido a Pago | AC1: Seguro Invalidez y Supervivencia (SIS) | AD1: Seguro Cesantia Empleador | AE1: Seguro Cesantia (Fondo Solidario) | AF1: Seguro accidentes del Trabajo | AG1: Capitalización Individual AFP | AH1: Expectativa de Vida | AI1: Costo Empresa
A2: 77656064-2 | B2: 3 | C2: 44606242-5 | D2: CHRISTIAN ROLANDO | E2: SAINT | F2: GERMAIN | H2: Supervisor de Comunicaciones | I2: Uno | J2: Fonasa | L2: Plazo Fijo | M2: 15/02/2026 | N2: 30/11/2026 | O2: 30 | P2: 0 | Q2: 0 | R2: 0 | S2: 700000 | T2: 175000 | U2: 875000 | V2: 875000 | W2: 91525 | X2: 61250 | Y2: 152775 | Z2: 0 | AA2: 152775 | AB2: 722225 | AC2: 13475 | AD2: 24500 | AE2: 1750 | AF2: 8138 | AG2: 875 | AH2: 7875 | AI2: 931613
A3: 77656064-2 | B3: 3 | C3: 44606258-1 | D3: GALO ANDRES | E3: TOBAR | F3: CISNEROS | H3: Supervisor de Comunicaciones | I3: Uno | J3: Fonasa | L3: Plazo Fijo | M3: 15/02/2026 | N3: 30/11/2026 | O3: 30 | P3: 0 | Q3: 0 | R3: 0 | S3: 700000 | T3: 175000 | U3: 875000 | V3: 875000 | W3: 91525 | X3: 61250 | Y3: 152775 | Z3: 0 | AA3: 152775 | AB3: 722225 | AC3: 13475 | AD3: 24500 | AE3: 1750 | AF3: 8138 | AG3: 875 | AH3: 7875 | AI3: 931613
S5: =+S2+S3 -> 1400000 | T5: =+T2+T3 -> 350000 | U5: =+U2+U3 -> 1750000 | V5: =+V2+V3 -> 1750000 | W5: =+W2+W3 -> 183050 | X5: =+X2+X3 -> 122500 | Y5: =+Y2+Y3 -> 305550 | Z5: =+Z2+Z3 -> 0 | ... AI5: =+AI2+AI3 -> 1863226
AB8: =+W5+X5+AD5+AE5+AF5+AG5+AH5+AC5 -> 418776
AB9: 418776

Sheet Centralizacion
C2: CENTRALIZACION PROYESCO
C3: MARZO 2025
B4: Cuentas | D4: D E B E | E4: H A B E R
C6: REMUNERACIONES | D6: =+'03.2026'!S5+'03.2026'!T5 -> 1750000
C7: LEYES SOCIALES | D7: =+'03.2026'!AH5+'03.2026'!AG5+'03.2026'!AF5+'03.2026'!AE5+'03.2026'!AD5+'03.2026'!AC5 -> 113226
C8: IMPUESTO UNICO A LOS TRABAJADORES | E8: 0
C9: IMPUESTO RELIQUIDADO
C10: PREVIRED POR PAGAR | E10: =+'03.2026'!W5+'03.2026'!X5+'03.2026'!AC5+'03.2026'!AD5+'03.2026'!AE5+'03.2026'!AF5+'03.2026'!AG5+'03.2026'!AH5 -> 418776 | F10: 418776 | G10: =+E10-F10 -> 0
C11: ANTICIPO DE SUELDO
C12: SUELDOS POR PAGAR | E12: =+'03.2026'!AB5 -> 1444450
D15: =SUM(D6:D14) -> 1863226 | E15: =SUM(E6:E14) -> 1863226 | G15: =+'03.2026'!AI5 -> 1863226
D16: =D15-G15 -> 0 | E16: =E15-G15 -> 0
C21: CENTRALIZACION FINIQUITO
C22: FEBRERO 2025
B24: Cuentas | D24: D E B E | E24: H A B E R
C26: FINIQUITOS | D26: 0
C27: FINIQUITOS POR PAGAR | E27: 0 | K27: =SUM(K24:K26) -> 0
D30: =SUM(D26:D29) -> 0 | E30: =SUM(E26:E29) -> 0
