Workbook

Sheet 04.2026
A1: razon social rut | B1: mes | C1: rut | D1: nombre | E1: apellido paterno | F1: apellido materno | G1: cargo | H1: fecha contratacion | I1: contrato hasta | J1: afp nombre | K1: prevision nombre | L1: isapre monto pactado | M1: Días Trabajados | N1: Sueldo Base | O1: Gratificación Mensual | P1: Renta Imponible | Q1: Suma de Haberes | R1: AFP | S1: Salud 7% (Fonasa) | T1: Suma Descuentos Legales, Impuestos y Por planilla | U1: Liquido a Pago | V1: Seguro accidentes del Trabajo | W1: Seguro Cesantia Empleador | X1: Seguro Cesantia (Fondo Solidario) | Y1: Seguro Invalidez y Supervivencia (SIS) | Z1: Capitalización Individual AFP | AA1: Expectativa de Vida | AB1: Costo Empresa
A2: 77656064-2 | B2: 4 | C2: 44606242-5 | D2: CHRISTIAN ROLANDO | E2: SAINT | F2: GERMAIN | G2: Supervisor de Comunicaciones | H2: 15/02/2026 | I2: 30/11/2026 | J2: Uno | K2: Fonasa | M2: 30 | N2: 700000 | O2: 175000 | P2: 875000 | Q2: 875000 | R2: 91525 | S2: 61250 | T2: 152775 | U2: 722225 | V2: 8138 | W2: 24500 | X2: 1750 | Y2: 14175 | Z2: 875 | AA2: 7875 | AB2: 932313
A3: 77656064-2 | B3: 4 | C3: 44606258-1 | D3: GALO ANDRES | E3: TOBAR | F3: CISNEROS | G3: Supervisor de Comunicaciones | H3: 15/02/2026 | I3: 30/11/2026 | J3: Uno | K3: Fonasa | M3: 30 | N3: 700000 | O3: 175000 | P3: 875000 | Q3: 875000 | R3: 91525 | S3: 61250 | T3: 152775 | U3: 722225 | V3: 8138 | W3: 24500 | X3: 1750 | Y3: 14175 | Z3: 875 | AA3: 7875 | AB3: 932313
N5: =+SUM(N2:N3) -> 1400000 | O5: =+SUM(O2:O3) -> 350000 | P5: =+SUM(P2:P3) -> 1750000 | Q5: =+SUM(Q2:Q3) -> 1750000 | R5: =+SUM(R2:R3) -> 183050 | S5: =+SUM(S2:S3) -> 122500 | T5: =+SUM(T2:T3) -> 305550 | U5: =+SUM(U2:U3) -> 1444450 | ... AB5: =+SUM(AB2:AB3) -> 1864626

Sheet Centralizacion
C2: CENTRALIZACION PROYESCO
C3: Abril 2026
B4: Cuentas | D4: D E B E | E4: H A B E R
C6: REMUNERACIONES | D6: =+'04.2026'!N5+'04.2026'!O5 -> 1750000
C7: LEYES SOCIALES | D7: =+'04.2026'!V5+'04.2026'!W5+'04.2026'!X5+'04.2026'!Y5+'04.2026'!Z5+'04.2026'!AA5 -> 114626
C8: IMPUESTO UNICO A LOS TRABAJADORES | E8: 0
C9: IMPUESTO RELIQUIDADO
C10: PREVIRED POR PAGAR | E10: =+'04.2026'!R5+'04.2026'!S5+'04.2026'!V5+'04.2026'!W5+'04.2026'!X5+'04.2026'!Y5+'04.2026'!Z5+'04.2026'!AA5 -> 420176 | F10: 420176 | G10: =+E10-F10 -> 0
C11: ANTICIPO DE SUELDO
C12: SUELDOS POR PAGAR | E12: =+'04.2026'!U5 -> 1444450
D15: =SUM(D6:D14) -> 1864626 | E15: =SUM(E6:E14) -> 1864626 | G15: =+'04.2026'!AB5 -> 1864626
D16: =D15-G15 -> 0 | E16: =E15-G15 -> 0
C21: CENTRALIZACION FINIQUITO
C22: Abril 2026
B24: Cuentas | D24: D E B E | E24: H A B E R
C26: FINIQUITOS | D26: 0
C27: FINIQUITOS POR PAGAR | E27: 0 | K27: =SUM(K24:K26) -> 0
D30: =SUM(D26:D29) -> 0 | E30: =SUM(E26:E29) -> 0
